{
  "companyId": "",
  "companyData": {
    "name": "Apeel"
  },
  "jobTitle": "Vice President, Legal",
  "category": {
    "id": 16,
    "name": "Legal",
    "slug": "legal"
  },
  "jobDescription": "<div class=\"content-intro\"><p>At Apeel, we look to nature to help the global food system extend quality, prevent waste, and ensure an abundant future for our planet.</p><p>We believe that our most essential ingredient in our recipe for success is our people. We strive to cultivate an environment where everyone is welcomed, and can bring their full, authentic selves into everything they do at Apeel. Humility, Ingenuity, Leadership, Teamwork and Grit are the values that define us and how we work with each other, customers, and communities across the globe.</p></div> <p><strong>About This Role </strong></p><p>At Apeel Sciences, the Head of Legal embodies the nexus of legal stewardship and strategic leadership, entrusted with the critical task of navigating our global business and operations through a complex legal landscape. Beyond the traditional purview of legal oversight, this role is a beacon of integrity, ensuring that our actions align with regulatory mandates and ethical standards while fostering an environment ripe for innovation and growth. From spearheading corporate governance initiatives to orchestrating intricate contract negotiations, you'll be instrumental in fortifying our legal framework and propelling us toward our strategic imperatives – navigating the complexities of the legal landscape with foresight and precision, all while championing our mission to create a more sustainable future through innovative solutions.</p><p><strong>What You’ll Do</strong></p><ul><li>Act as a key partner to the global business, advising and leading to help the company proactively and scalably assess and manage legal risk and compliance, and drive competitiveness.</li><li>Couple depth and breadth of corporate legal experience and strong collaboration with a thorough understanding of our corporate values, strategy, and goals, as well as with our technologies, products, business models, and core operations.</li><li>Develop, implement, and maintain a comprehensive legal compliance program across the company.</li><li>Oversee and execute corporate governance matters, including Board of Directors matters and the formation and management of subsidiaries, ensuring adherence to regulatory requirements.</li><li>Draft and negotiate right-sized legal agreements and documents -- going beyond form templates where appropriate -- encompassing contracts with customers, vendors, partners, and various stakeholders.</li><li>Develop and refine processes and procedures for handling commercial agreements, optimizing departmental efficiency.</li><li>Oversee the management of our intellectual property portfolio, including engagement with our R&amp;D activities to ensure a healthy and protected innovation pipeline.</li><li>Oversee and manage our corporate insurance portfolio and policies.</li><li>Offer legal guidance on employment matters, including drafting and negotiating employment contracts, and related documentation.</li><li>Provide legal assistance in fundraising, M&amp;A, and related activities, ensuring compliance and mitigating risks throughout the process.</li><li>Provide strategic legal guidance and support in crisis and reputation management situations.</li><li>Oversee and manage litigations, where needed.</li><li>Lead and grow a lean, high-performing team.</li><li>Oversee external legal counsel, optimizing their efficiency and quality of work.</li></ul><p><strong>What You Bring</strong></p><ul><li>Licensed to practice law in California, with a minimum of 15 years of diverse and proven legal experience across contracts and deal-making, corporate governance, equity plans, compliance, intellectual property, litigation, M&amp;A, and SEC compliance and reporting.</li><li>Experience in a high-growth or turnaround business setting is preferred, particularly with taking a company from private to public offering.</li><li>Experience in FoodTech, AgTech, or other “deep tech” companies with products and services -- as well as software products and services -- a strong asset.</li><li>Exemplary professionalism and strict preservation of confidentiality.</li><li>Thoroughness and rigor in the analysis of a legal or business matter.</li><li>Reliable exercise of sound judgment and ability to give actionable advice in ambiguous situations.</li><li>Ability to work independently while contributing successfully cross-functionally.</li><li>Strong organizational, written, and verbal communication skills essential for effective legal counsel and collaboration across the organization, including external-facing representation of the company.</li><li>Customer service- and a results-oriented mindset, focused on enabling business objectives while ensuring legal compliance and risk mitigation.</li><li>Experience and willingness to lead hands-on, large, and small-scale legal projects aligned with company objectives and key results.</li><li>Ability to manage multiple projects at once, follow through, and meet deadlines.</li><li>Experience attracting and developing talent.</li></ul><div id=\"message-list-preview-list_1671590384.743559\" class=\"c-virtual_list__item\" data-qa=\"virtual-list-item\" data-item-key=\"1671590384.743559\"><div class=\"c-message_kit__background c-message_kit__background--hovered p-message_pane_message__message c-message_kit__message\" data-qa=\"message_container\" data-qa-unprocessed=\"false\" data-qa-placeholder=\"false\"> </div></div><div id=\"message-list-preview-list_1671590412.338049\" class=\"c-virtual_list__item c-virtual_list__item--initial-activeitem\" data-qa=\"virtual-list-item\" data-item-key=\"1671590412.338049\"><div class=\"c-message_kit__background p-message_pane_message__message c-message_kit__message\" data-qa=\"message_container\" data-qa-unprocessed=\"false\" data-qa-placeholder=\"false\"><div class=\"c-message_kit__hover\" data-qa-hover=\"true\"><div class=\"c-message_kit__actions c-message_kit__actions--above\"><div class=\"c-message_kit__gutter\"><div class=\"c-message_kit__gutter__left\">Our total rewards packages may include comprehensive health plans, 401k matching, equity, flexible PTO, sick leave, paid parental leave, and more! Compensation for this role is expected to be between $240,000 and $280,000. Actual base pay may be higher or lower depending on geographic locations, skills, experience, and other factors permitted by law.</div><div class=\"c-message_kit__gutter__right\" data-qa=\"message_content\"><div class=\"c-message_kit__blocks c-message_kit__blocks--rich_text\"><div class=\"c-message__message_blocks c-message__message_blocks--rich_text\" data-qa=\"message-text\"><div class=\"p-block_kit_renderer\" data-qa=\"block-kit-renderer\"><div class=\"p-block_kit_renderer__block_wrapper p-block_kit_renderer__block_wrapper--first\"><div class=\"p-rich_text_block\"><div class=\"p-rich_text_section\"><div id=\"message-list-preview-list_1671590412.338049\" class=\"c-virtual_list__item c-virtual_list__item--initial-activeitem\" data-qa=\"virtual-list-item\" data-item-key=\"1671590412.338049\"><div class=\"c-message_kit__background p-message_pane_message__message c-message_kit__message\" data-qa=\"message_container\" data-qa-unprocessed=\"false\" data-qa-placeholder=\"false\"><div class=\"c-message_kit__hover\" data-qa-hover=\"true\"><div class=\"c-message_kit__actions c-message_kit__actions--above\"><div class=\"c-message_kit__gutter\"><div class=\"c-message_kit__gutter__right\" data-qa=\"message_content\"><div class=\"c-message_kit__blocks c-message_kit__blocks--rich_text\"><div class=\"c-message__message_blocks c-message__message_blocks--rich_text\" data-qa=\"message-text\"><div class=\"p-block_kit_renderer\" data-qa=\"block-kit-renderer\"><div class=\"p-block_kit_renderer__block_wrapper p-block_kit_renderer__block_wrapper--first\"><div class=\"p-rich_text_block\"><div class=\"p-rich_text_section\"> </div><div class=\"p-rich_text_section\">At Apeel, we value potential and recognize that great candidates come from diverse backgrounds. We seek to build a diverse and inclusive workforce where everyone can thrive. If you are enthusiastic about this role and believe your unique perspective would be an asset to our team, but don't meet every qualification, please don't hesitate to apply!</div></div></div></div></div></div></div></div></div></div></div></div></div></div></div></div></div></div></div></div></div></div></div></div> <div class=\"content-conclusion\"><p><span style=\"font-weight: 400;\">Apeel believes that the scale of our impact is determined by the teams that work with us. As such, we seek to build high-performing teams of people from various experiences and backgrounds who can collectively push our company into new realms. We seek a diverse pool of applicants and consider all qualified candidates regardless of race, ancestry, color, gender identity or expression, sexual orientation, religion, national origin, citizenship, disability, Veteran status, marital status, or any other protected status. If you have any need for accommodations, you can let us know if you choose and know that we will do our best to assist you.</span></p></div>",
  "jobType": "Full-time",
  "salary": null,
  "locationInfo": {
    "location": "remote",
    "onSiteLocation": [
      "Remote, US"
    ]
  },
  "email": "l.c.vanroomen@gmail.com",
  "fullName": "Laurens van Roomen",
  "timestamp": 0,
  "id": "",
  "paid": true,
  "published": true,
  "listed": true,
  "closed": false,
  "applicationMethod": "website",
  "apply": "https://boards.greenhouse.io/apeel/jobs/6087768",
  "external": false,
  "coupon": "",
  "invoiceInfo": {}
}